stockmanager/Manager.py
stockmanager/Portfolio.py
stockmanager/Ticker.py
stockmanager/__init__.py
stockmanager/base.py
stockmanager/helpers.py
stockmanager/visualization/__init__.py
stockmanager/visualization/_arg_validator.py
stockmanager/visualization/plots.py
stockmanager-0.1.0.dist-info/AUTHORS.rst
stockmanager-0.1.0.dist-info/LICENSE.txt
stockmanager-0.1.0.dist-info/METADATA
stockmanager-0.1.0.dist-info/WHEEL
stockmanager-0.1.0.dist-info/top_level.txt
stockmanager-0.1.0.dist-info/RECORD
