Metadata-Version: 2.1
Name: stockmanager
Version: 0.1.0
Summary: Stock Manager
Home-page: https://github.com/wiccy46/stockmanager
Author: Jiajun Yang
Author-email: thejyang@gmail.com
License: mit
Project-URL: Documentation, https://github.com/wiccy46/stockmanager
Platform: any
Classifier: Development Status :: 3 - Alpha
Classifier: Programming Language :: Python
Classifier: Programming Language :: Python :: 3
Classifier: Operating System :: OS Independent
Classifier: Topic :: Office/Business :: Financial
Classifier: Topic :: Office/Business :: Financial :: Investment
Provides-Extra: testing
Requires-Dist: pytest ; extra == 'testing'
Requires-Dist: pytest-cov ; extra == 'testing'
